setup.py
gsbn_probability/Binomialdistribution.py
gsbn_probability/Gaussiandistribution.py
gsbn_probability/Generaldistribution.py
gsbn_probability/__init__.py
gsbn_probability.egg-info/PKG-INFO
gsbn_probability.egg-info/SOURCES.txt
gsbn_probability.egg-info/dependency_links.txt
gsbn_probability.egg-info/not-zip-safe
gsbn_probability.egg-info/top_level.txt